{
"type": "FeatureCollection",
"crs": { "type": "name", "properties": { "name": "urn:ogc:def:crs:OGC:1.3:CRS84" } },
"features": [
{ "type": "Feature", "properties": { "AIANNHCE": "4140", "AIANNHNS": "01934342", "GEOID": "4140R", "NAME": "Taos", "NAMELSAD": "Taos Pueblo", "LSAD": "84", "COMPTYP": "R", "CLASSFP": "D8", "AIANNHR": "F", "MTFCC": "G2101", "FUNCSTAT": "A", "ALAND": 401225858.0, "AWATER": 154305.0, "INTPTLAT": "+36.4726906", "INTPTLON": "-105.5250260" }, "geometry": { "type": "Point", "coordinates": [ -105.51119474876695, 36.460342323317782 ] } }
]
}
